routeros_telegraf_exporter/__init__.py
routeros_telegraf_exporter/cli.py
routeros_telegraf_exporter/models.py
routeros_telegraf_exporter/probe_cli.py
routeros_telegraf_exporter/routeros_exporter.py
routeros_telegraf_exporter/utils.py
routeros_telegraf_exporter/views.py
routeros_telegraf_exporter-0.1.13.dist-info/AUTHORS.rst
routeros_telegraf_exporter-0.1.13.dist-info/LICENSE
routeros_telegraf_exporter-0.1.13.dist-info/METADATA
routeros_telegraf_exporter-0.1.13.dist-info/WHEEL
routeros_telegraf_exporter-0.1.13.dist-info/entry_points.txt
routeros_telegraf_exporter-0.1.13.dist-info/top_level.txt
routeros_telegraf_exporter-0.1.13.dist-info/RECORD
