Metadata-Version: 2.1
Name: routeros-telegraf-exporter
Version: 0.1.13
Summary: RouterOS metrics exporter enables metrics export to Telegraf
Home-page: https://github.com/kepsic/routeros_telegraf_exporter
Author: Andres Kepler
Author-email: andres@kepler.ee
License: MIT license
Keywords: routeros_telegraf_exporter,web service
Platform: UNKNOWN
Classifier: Development Status :: 2 - Pre-Alpha
Classifier: Intended Audience :: Developers
Classifier: License :: OSI Approved :: MIT License
Classifier: Natural Language :: English
Classifier: Programming Language :: Python :: 3
Classifier: Programming Language :: Python :: 3.5
Classifier: Programming Language :: Python :: 3.6
Classifier: Programming Language :: Python :: 3.7
Classifier: Programming Language :: Python :: 3.8
Requires-Python: >=3.7
Requires-Dist: venusian
Requires-Dist: simplejson
Requires-Dist: pyramid
Requires-Dist: cornice
Requires-Dist: waitress
Requires-Dist: routeros-api
Requires-Dist: pyyaml
